blender_downloader/__init__.py
blender_downloader/__main__.py
blender_downloader-1.0.5.dist-info/METADATA
blender_downloader-1.0.5.dist-info/WHEEL
blender_downloader-1.0.5.dist-info/entry_points.txt
blender_downloader-1.0.5.dist-info/licenses/LICENSE
blender_downloader-1.0.5.dist-info/RECORD
