Metadata-Version: 2.3
Name: blender-downloader
Version: 1.0.5
Summary: Blender portable release downloader.
Project-URL: Source, https://github.com/mondeja/blender-downloader
Project-URL: Documentation, https://github.com/mondeja/blender-downloader#usage
Project-URL: Bug tracker, https://github.com/mondeja/blender-downloader/issues
Project-URL: Changelog, https://github.com/mondeja/blender-downloader/releases
Author-email: Álvaro Mondéjar Rubio <mondejar1994@gmail.com>
Maintainer-email: Álvaro Mondéjar Rubio <mondejar1994@gmail.com>
License: BSD-3-Clause
Keywords: blender,cli,downloader,installer,portable,release
Classifier: Development Status :: 5 - Production/Stable
Classifier: Environment :: Console
Classifier: Intended Audience :: Developers
Classifier: Intended Audience :: End Users/Desktop
Classifier: Intended Audience :: System Administrators
Classifier: License :: OSI Approved :: BSD License
Classifier: Operating System :: OS Independent
Classifier: Programming Language :: Python
Classifier: Programming Language :: Python :: 3 :: Only
Classifier: Programming Language :: Python :: 3.8
Classifier: Programming Language :: Python :: 3.9
Classifier: Programming Language :: Python :: 3.10
Classifier: Programming Language :: Python :: 3.11
Classifier: Programming Language :: Python :: 3.12
Classifier: Programming Language :: Python :: 3.13
Classifier: Topic :: Internet :: WWW/HTTP :: Dynamic Content
Requires-Python: >=3.8
Requires-Dist: appdirs<2,>=1
Requires-Dist: diskcache<6,>=5
Requires-Dist: dmglib<1,>=0.9.3; sys_platform == 'darwin'
Requires-Dist: importlib-metadata-argparse-version<3,>=2
Requires-Dist: tqdm<5,>=4
